{
  "root" : {
    "name" : "ThermostatSetback",
    "namespace" : "com.bosch.iot.suite.edge.services.zwave.da.items",
    "version" : "1.0.1",
    "prettyFormat" : "com.bosch.iot.suite.edge.services.zwave.da.items:ThermostatSetback:1.0.1"
  },
  "models" : {
    "com.bosch.iot.suite.edge.services.zwave.da.items.data:OverrideState:1.0.0" : {
      "targetPlatformKey" : null,
      "stereotypes" : [ ],
      "mappingReference" : null,
      "vortolang" : "1.0",
      "id" : {
        "name" : "OverrideState",
        "namespace" : "com.bosch.iot.suite.edge.services.zwave.da.items.data",
        "version" : "1.0.0",
        "prettyFormat" : "com.bosch.iot.suite.edge.services.zwave.da.items.data:OverrideState:1.0.0"
      },
      "type" : "Datatype",
      "displayName" : "Override State",
      "description" : "Defines a override(setback). The setpoint is the temperature a device will try to maintain. The override(setback) is a deviation from the setpoint. When a override(setback) is in use, the device will apply the override(setback) to the setpoint, resulting in a different temperature.",
      "category" : null,
      "fileName" : "OverrideState.type",
      "modelType" : "EntityModel",
      "references" : [ ],
      "properties" : [ {
        "targetPlatformKey" : null,
        "stereotypes" : [ ],
        "mappingReference" : null,
        "mandatory" : true,
        "name" : "state",
        "description" : "The override state.",
        "type" : "BYTE",
        "constraints" : [ {
          "type" : "NULLABLE",
          "value" : "false"
        } ],
        "attributes" : [ {
          "type" : "READABLE",
          "value" : true
        } ],
        "multiple" : false,
        "primitive" : true
      }, {
        "targetPlatformKey" : null,
        "stereotypes" : [ ],
        "mappingReference" : null,
        "mandatory" : true,
        "name" : "type",
        "description" : "The override type.",
        "type" : "INT",
        "constraints" : [ {
          "type" : "NULLABLE",
          "value" : "false"
        } ],
        "attributes" : [ {
          "type" : "READABLE",
          "value" : true
        } ],
        "multiple" : false,
        "primitive" : true
      } ],
      "superType" : null
    },
    "com.bosch.iot.suite.edge.services.zwave.da.items:ThermostatSetback:1.0.1" : {
      "targetPlatformKey" : null,
      "stereotypes" : [ ],
      "mappingReference" : null,
      "vortolang" : "1.0",
      "id" : {
        "name" : "ThermostatSetback",
        "namespace" : "com.bosch.iot.suite.edge.services.zwave.da.items",
        "version" : "1.0.1",
        "prettyFormat" : "com.bosch.iot.suite.edge.services.zwave.da.items:ThermostatSetback:1.0.1"
      },
      "type" : "Functionblock",
      "displayName" : "Z-Wave Thermostat Setback",
      "description" : "Provides support for the Z-Wave Thermostat Setback Command Class.",
      "category" : null,
      "fileName" : "ThermostatSetback.fbmodel",
      "modelType" : "FunctionblockModel",
      "references" : [ {
        "name" : "OverrideState",
        "namespace" : "com.bosch.iot.suite.edge.services.zwave.da.items.data",
        "version" : "1.0.0",
        "prettyFormat" : "com.bosch.iot.suite.edge.services.zwave.da.items.data:OverrideState:1.0.0"
      }, {
        "name" : "OverrideState",
        "namespace" : "com.bosch.iot.suite.edge.services.zwave.da.items.data",
        "version" : "1.0.0",
        "prettyFormat" : "com.bosch.iot.suite.edge.services.zwave.da.items.data:OverrideState:1.0.0"
      } ],
      "configurationProperties" : [ {
        "targetPlatformKey" : null,
        "stereotypes" : [ ],
        "mappingReference" : null,
        "mandatory" : true,
        "name" : "state",
        "description" : "Represents the state of the Thermostat Setback (Override).",
        "type" : {
          "name" : "OverrideState",
          "namespace" : "com.bosch.iot.suite.edge.services.zwave.da.items.data",
          "version" : "1.0.0",
          "prettyFormat" : "com.bosch.iot.suite.edge.services.zwave.da.items.data:OverrideState:1.0.0"
        },
        "constraints" : [ ],
        "attributes" : [ {
          "type" : "READABLE",
          "value" : true
        }, {
          "type" : "WRITABLE",
          "value" : true
        }, {
          "type" : "EVENTABLE",
          "value" : true
        } ],
        "multiple" : false,
        "primitive" : false
      }, {
        "targetPlatformKey" : null,
        "stereotypes" : [ ],
        "mappingReference" : null,
        "mandatory" : true,
        "name" : "name",
        "description" : null,
        "type" : "STRING",
        "constraints" : [ ],
        "attributes" : [ {
          "type" : "READABLE",
          "value" : true
        }, {
          "type" : "WRITABLE",
          "value" : true
        }, {
          "type" : "EVENTABLE",
          "value" : true
        } ],
        "multiple" : false,
        "primitive" : true
      }, {
        "targetPlatformKey" : null,
        "stereotypes" : [ ],
        "mappingReference" : null,
        "mandatory" : true,
        "name" : "tags",
        "description" : null,
        "type" : "STRING",
        "constraints" : [ ],
        "attributes" : [ {
          "type" : "READABLE",
          "value" : true
        }, {
          "type" : "WRITABLE",
          "value" : true
        }, {
          "type" : "EVENTABLE",
          "value" : true
        } ],
        "multiple" : true,
        "primitive" : true
      } ],
      "statusProperties" : [ ],
      "faultProperties" : [ ],
      "events" : [ ],
      "operations" : [ ],
      "superType" : {
        "name" : "FunctionalItem",
        "namespace" : "com.bosch.iot.suite.edge.services.fim",
        "version" : "1.0.0",
        "prettyFormat" : "com.bosch.iot.suite.edge.services.fim:FunctionalItem:1.0.0"
      }
    },
    "com.bosch.iot.suite.edge.services.fim:FunctionalItem:1.0.0" : {
      "targetPlatformKey" : null,
      "stereotypes" : [ ],
      "mappingReference" : null,
      "vortolang" : "1.0",
      "id" : {
        "name" : "FunctionalItem",
        "namespace" : "com.bosch.iot.suite.edge.services.fim",
        "version" : "1.0.0",
        "prettyFormat" : "com.bosch.iot.suite.edge.services.fim:FunctionalItem:1.0.0"
      },
      "type" : "Functionblock",
      "displayName" : "Functional Item",
      "description" : null,
      "category" : null,
      "fileName" : "FunctionalItem.fbmodel",
      "modelType" : "FunctionblockModel",
      "references" : [ ],
      "configurationProperties" : [ {
        "targetPlatformKey" : null,
        "stereotypes" : [ ],
        "mappingReference" : null,
        "mandatory" : true,
        "name" : "name",
        "description" : null,
        "type" : "STRING",
        "constraints" : [ ],
        "attributes" : [ {
          "type" : "READABLE",
          "value" : true
        }, {
          "type" : "WRITABLE",
          "value" : true
        }, {
          "type" : "EVENTABLE",
          "value" : true
        } ],
        "multiple" : false,
        "primitive" : true
      }, {
        "targetPlatformKey" : null,
        "stereotypes" : [ ],
        "mappingReference" : null,
        "mandatory" : true,
        "name" : "tags",
        "description" : null,
        "type" : "STRING",
        "constraints" : [ ],
        "attributes" : [ {
          "type" : "READABLE",
          "value" : true
        }, {
          "type" : "WRITABLE",
          "value" : true
        }, {
          "type" : "EVENTABLE",
          "value" : true
        } ],
        "multiple" : true,
        "primitive" : true
      } ],
      "statusProperties" : [ ],
      "faultProperties" : [ ],
      "events" : [ ],
      "operations" : [ ],
      "superType" : null
    }
  }
}