{
  "root" : {
    "name" : "Action",
    "namespace" : "com.bosch.iot.suite.edge.update",
    "version" : "1.0.0",
    "prettyFormat" : "com.bosch.iot.suite.edge.update:Action:1.0.0"
  },
  "models" : {
    "com.bosch.iot.suite.edge.update:Action:1.0.0" : {
      "targetPlatformKey" : null,
      "stereotypes" : [ ],
      "mappingReference" : null,
      "vortolang" : "1.0",
      "id" : {
        "name" : "Action",
        "namespace" : "com.bosch.iot.suite.edge.update",
        "version" : "1.0.0",
        "prettyFormat" : "com.bosch.iot.suite.edge.update:Action:1.0.0"
      },
      "type" : "Datatype",
      "displayName" : "Action",
      "description" : "Represents an action that is performed during an update procedure",
      "category" : null,
      "fileName" : "Action.type",
      "modelType" : "EntityModel",
      "references" : [ {
        "name" : "Component",
        "namespace" : "com.bosch.iot.suite.edge.update",
        "version" : "1.0.0",
        "prettyFormat" : "com.bosch.iot.suite.edge.update:Component:1.0.0"
      }, {
        "name" : "ActionStatusType",
        "namespace" : "com.bosch.iot.suite.edge.update",
        "version" : "1.0.0",
        "prettyFormat" : "com.bosch.iot.suite.edge.update:ActionStatusType:1.0.0"
      } ],
      "properties" : [ {
        "targetPlatformKey" : null,
        "stereotypes" : [ ],
        "mappingReference" : null,
        "mandatory" : true,
        "name" : "component",
        "description" : null,
        "type" : {
          "name" : "Component",
          "namespace" : "com.bosch.iot.suite.edge.update",
          "version" : "1.0.0",
          "prettyFormat" : "com.bosch.iot.suite.edge.update:Component:1.0.0"
        },
        "constraints" : [ ],
        "attributes" : [ ],
        "multiple" : false,
        "primitive" : false
      }, {
        "targetPlatformKey" : null,
        "stereotypes" : [ ],
        "mappingReference" : null,
        "mandatory" : true,
        "name" : "status",
        "description" : null,
        "type" : {
          "name" : "ActionStatusType",
          "namespace" : "com.bosch.iot.suite.edge.update",
          "version" : "1.0.0",
          "prettyFormat" : "com.bosch.iot.suite.edge.update:ActionStatusType:1.0.0"
        },
        "constraints" : [ ],
        "attributes" : [ ],
        "multiple" : false,
        "primitive" : false
      }, {
        "targetPlatformKey" : null,
        "stereotypes" : [ ],
        "mappingReference" : null,
        "mandatory" : true,
        "name" : "progress",
        "description" : null,
        "type" : "INT",
        "constraints" : [ ],
        "attributes" : [ ],
        "multiple" : false,
        "primitive" : true
      }, {
        "targetPlatformKey" : null,
        "stereotypes" : [ ],
        "mappingReference" : null,
        "mandatory" : true,
        "name" : "message",
        "description" : null,
        "type" : "STRING",
        "constraints" : [ ],
        "attributes" : [ ],
        "multiple" : false,
        "primitive" : true
      } ],
      "superType" : null
    },
    "com.bosch.iot.suite.edge.update:ActionStatusType:1.0.0" : {
      "targetPlatformKey" : null,
      "stereotypes" : [ ],
      "mappingReference" : null,
      "vortolang" : "1.0",
      "id" : {
        "name" : "ActionStatusType",
        "namespace" : "com.bosch.iot.suite.edge.update",
        "version" : "1.0.0",
        "prettyFormat" : "com.bosch.iot.suite.edge.update:ActionStatusType:1.0.0"
      },
      "type" : "Datatype",
      "displayName" : "ActionStatusType",
      "description" : "Represents the possible status values for an update action",
      "category" : null,
      "fileName" : "ActionStatusType.type",
      "modelType" : "EnumModel",
      "references" : [ ],
      "literals" : [ {
        "name" : "IDENTIFIED",
        "description" : null,
        "parent" : {
          "name" : "ActionStatusType",
          "namespace" : "com.bosch.iot.suite.edge.update",
          "version" : "1.0.0",
          "prettyFormat" : "com.bosch.iot.suite.edge.update:ActionStatusType:1.0.0"
        }
      }, {
        "name" : "DOWNLOADING",
        "description" : null,
        "parent" : {
          "name" : "ActionStatusType",
          "namespace" : "com.bosch.iot.suite.edge.update",
          "version" : "1.0.0",
          "prettyFormat" : "com.bosch.iot.suite.edge.update:ActionStatusType:1.0.0"
        }
      }, {
        "name" : "DOWNLOAD_FAILURE",
        "description" : null,
        "parent" : {
          "name" : "ActionStatusType",
          "namespace" : "com.bosch.iot.suite.edge.update",
          "version" : "1.0.0",
          "prettyFormat" : "com.bosch.iot.suite.edge.update:ActionStatusType:1.0.0"
        }
      }, {
        "name" : "DOWNLOAD_SUCCESS",
        "description" : null,
        "parent" : {
          "name" : "ActionStatusType",
          "namespace" : "com.bosch.iot.suite.edge.update",
          "version" : "1.0.0",
          "prettyFormat" : "com.bosch.iot.suite.edge.update:ActionStatusType:1.0.0"
        }
      }, {
        "name" : "UPDATING",
        "description" : null,
        "parent" : {
          "name" : "ActionStatusType",
          "namespace" : "com.bosch.iot.suite.edge.update",
          "version" : "1.0.0",
          "prettyFormat" : "com.bosch.iot.suite.edge.update:ActionStatusType:1.0.0"
        }
      }, {
        "name" : "UPDATE_FAILURE",
        "description" : null,
        "parent" : {
          "name" : "ActionStatusType",
          "namespace" : "com.bosch.iot.suite.edge.update",
          "version" : "1.0.0",
          "prettyFormat" : "com.bosch.iot.suite.edge.update:ActionStatusType:1.0.0"
        }
      }, {
        "name" : "UPDATE_SUCCESS",
        "description" : null,
        "parent" : {
          "name" : "ActionStatusType",
          "namespace" : "com.bosch.iot.suite.edge.update",
          "version" : "1.0.0",
          "prettyFormat" : "com.bosch.iot.suite.edge.update:ActionStatusType:1.0.0"
        }
      }, {
        "name" : "REMOVING",
        "description" : null,
        "parent" : {
          "name" : "ActionStatusType",
          "namespace" : "com.bosch.iot.suite.edge.update",
          "version" : "1.0.0",
          "prettyFormat" : "com.bosch.iot.suite.edge.update:ActionStatusType:1.0.0"
        }
      }, {
        "name" : "REMOVAL_FAILURE",
        "description" : null,
        "parent" : {
          "name" : "ActionStatusType",
          "namespace" : "com.bosch.iot.suite.edge.update",
          "version" : "1.0.0",
          "prettyFormat" : "com.bosch.iot.suite.edge.update:ActionStatusType:1.0.0"
        }
      }, {
        "name" : "REMOVAL_SUCCESS",
        "description" : null,
        "parent" : {
          "name" : "ActionStatusType",
          "namespace" : "com.bosch.iot.suite.edge.update",
          "version" : "1.0.0",
          "prettyFormat" : "com.bosch.iot.suite.edge.update:ActionStatusType:1.0.0"
        }
      }, {
        "name" : "ACTIVATING",
        "description" : null,
        "parent" : {
          "name" : "ActionStatusType",
          "namespace" : "com.bosch.iot.suite.edge.update",
          "version" : "1.0.0",
          "prettyFormat" : "com.bosch.iot.suite.edge.update:ActionStatusType:1.0.0"
        }
      }, {
        "name" : "ACTIVATION_FAILURE",
        "description" : null,
        "parent" : {
          "name" : "ActionStatusType",
          "namespace" : "com.bosch.iot.suite.edge.update",
          "version" : "1.0.0",
          "prettyFormat" : "com.bosch.iot.suite.edge.update:ActionStatusType:1.0.0"
        }
      }, {
        "name" : "ACTIVATION_SUCCESS",
        "description" : null,
        "parent" : {
          "name" : "ActionStatusType",
          "namespace" : "com.bosch.iot.suite.edge.update",
          "version" : "1.0.0",
          "prettyFormat" : "com.bosch.iot.suite.edge.update:ActionStatusType:1.0.0"
        }
      } ]
    },
    "com.bosch.iot.suite.edge.update:Component:1.0.0" : {
      "targetPlatformKey" : null,
      "stereotypes" : [ ],
      "mappingReference" : null,
      "vortolang" : "1.0",
      "id" : {
        "name" : "Component",
        "namespace" : "com.bosch.iot.suite.edge.update",
        "version" : "1.0.0",
        "prettyFormat" : "com.bosch.iot.suite.edge.update:Component:1.0.0"
      },
      "type" : "Datatype",
      "displayName" : "Component",
      "description" : "Represents a desired state component",
      "category" : null,
      "fileName" : "Component.type",
      "modelType" : "EntityModel",
      "references" : [ ],
      "properties" : [ {
        "targetPlatformKey" : null,
        "stereotypes" : [ ],
        "mappingReference" : null,
        "mandatory" : true,
        "name" : "id",
        "description" : null,
        "type" : "STRING",
        "constraints" : [ ],
        "attributes" : [ ],
        "multiple" : false,
        "primitive" : true
      }, {
        "targetPlatformKey" : null,
        "stereotypes" : [ ],
        "mappingReference" : null,
        "mandatory" : true,
        "name" : "version",
        "description" : null,
        "type" : "STRING",
        "constraints" : [ ],
        "attributes" : [ ],
        "multiple" : false,
        "primitive" : true
      } ],
      "superType" : null
    }
  }
}